mle/__init__.py
mle/multi_layer_encoder.py
MultiEncoder-0.0.6.dist-info/LICENCE.txt
MultiEncoder-0.0.6.dist-info/METADATA
MultiEncoder-0.0.6.dist-info/WHEEL
MultiEncoder-0.0.6.dist-info/top_level.txt
MultiEncoder-0.0.6.dist-info/RECORD
