Metadata-Version: 2.1
Name: MultiEncoder
Version: 0.0.6
Summary: MultiEncoder
Author: Mosleh Mahamud
Author-email: mosleh.edu@gmail.com
License: UNKNOWN
Platform: UNKNOWN
Classifier: Programming Language :: Python :: 3
Classifier: License :: OSI Approved :: MIT License
Classifier: Operating System :: OS Independent
Requires-Python: >=3.7
License-File: LICENCE.txt
